dyndnsc_growl.py
dyndnsc_growl-0.1.dist-info/DESCRIPTION.rst
dyndnsc_growl-0.1.dist-info/METADATA
dyndnsc_growl-0.1.dist-info/RECORD
dyndnsc_growl-0.1.dist-info/WHEEL
dyndnsc_growl-0.1.dist-info/entry_points.txt
dyndnsc_growl-0.1.dist-info/metadata.json
dyndnsc_growl-0.1.dist-info/top_level.txt
dyndnsc_growl-0.1.dist-info/zip-safe
